django_session_timeout/__init__.py
django_session_timeout/middleware.py
django_session_timeout_joinup-1.0.0.dist-info/LICENSE
django_session_timeout_joinup-1.0.0.dist-info/METADATA
django_session_timeout_joinup-1.0.0.dist-info/WHEEL
django_session_timeout_joinup-1.0.0.dist-info/top_level.txt
django_session_timeout_joinup-1.0.0.dist-info/RECORD
